mineflayer/__init__.py
mineflayer/__main__.py
mineflayer/api-test.py
mineflayer/api.py
mineflayer/bot.py
mineflayer/discordbot.py
mineflayer/test-console.py
mineflayer/test.py
mineflayer/utils.py
mineflayer-0.0.14.dist-info/LICENSE
mineflayer-0.0.14.dist-info/METADATA
mineflayer-0.0.14.dist-info/WHEEL
mineflayer-0.0.14.dist-info/RECORD
