Metadata-Version: 2.1
Name: mineflayer
Version: 0.0.14
Summary: 🤖 Create Minecraft bots with a powerful, stable, and high level Python API.
License: MIT
Author: Silke pilon
Author-email: silkepilon2009@gmail.com
Requires-Python: >=3.10,<4.0
Classifier: License :: OSI Approved :: MIT License
Classifier: Programming Language :: Python :: 3
Classifier: Programming Language :: Python :: 3.10
Classifier: Programming Language :: Python :: 3.11
Requires-Dist: claude-api (>=1.0.17,<2.0.0)
Requires-Dist: click (>=8.1.7,<9.0.0)
Requires-Dist: discord-py (>=2.3.2,<3.0.0)
Requires-Dist: fastapi (>=0.103.1,<0.104.0)
Requires-Dist: fuzzyfinder (>=2.1.0,<3.0.0)
Requires-Dist: g4f (>=0.0.3.4,<0.0.4.0)
Requires-Dist: javascript (>=1!1.0.3,<1!2.0.0)
Requires-Dist: prompt-toolkit (>=3.0.39,<4.0.0)
Requires-Dist: pydantic (>=2.3.0,<3.0.0)
Requires-Dist: pyexecjs (>=1.5.1,<2.0.0)
Requires-Dist: rich (>=13.5.2,<14.0.0)
Requires-Dist: structlog (>=23.1.0,<24.0.0)
Requires-Dist: tinydb (>=4.8.0,<5.0.0)
Requires-Dist: tqdm (>=4.66.1,<5.0.0)
Requires-Dist: uvicorn (>=0.23.2,<0.24.0)
